pep249/__init__.py
pep249/connection.py
pep249/cursor.py
pep249/exceptions.py
pep249/extensions.py
pep249/transactions.py
pep249/type_constructors.py
pep249/types.py
pep249/aiopep249/__init__.py
pep249/aiopep249/connection.py
pep249/aiopep249/cursor.py
pep249/aiopep249/exceptions.py
pep249/aiopep249/extensions.py
pep249/aiopep249/transactions.py
pep249/aiopep249/type_constructors.py
pep249/aiopep249/types.py
pep249abc-0.0.1b3.dist-info/LICENSE
pep249abc-0.0.1b3.dist-info/METADATA
pep249abc-0.0.1b3.dist-info/WHEEL
pep249abc-0.0.1b3.dist-info/top_level.txt
pep249abc-0.0.1b3.dist-info/RECORD
