Metadata-Version: 2.1
Name: pep249abc
Version: 0.0.1b3
Summary: Abstract implementation of the DB 2.0 API outlined in PEP-249.
Home-page: https://github.com/thesketh/pep249
Author: Travis Hesketh
Author-email: travis@hesketh.scot
License: UNKNOWN
Platform: UNKNOWN
Classifier: Programming Language :: Python :: 3
Classifier: Programming Language :: Python :: 3.7
Classifier: Development Status :: 4 - Beta
Classifier: Natural Language :: English
Classifier: Intended Audience :: Developers
Classifier: Operating System :: OS Independent
Classifier: Topic :: Software Development :: Libraries
Classifier: License :: OSI Approved :: MIT License
Classifier: Typing :: Typed
Requires-Python: >=3.7
